attrs_sqlalchemy.py
attrs_sqlalchemy-0.1.0.dist-info/DESCRIPTION.rst
attrs_sqlalchemy-0.1.0.dist-info/LICENSE.txt
attrs_sqlalchemy-0.1.0.dist-info/METADATA
attrs_sqlalchemy-0.1.0.dist-info/RECORD
attrs_sqlalchemy-0.1.0.dist-info/WHEEL
attrs_sqlalchemy-0.1.0.dist-info/metadata.json
attrs_sqlalchemy-0.1.0.dist-info/top_level.txt
